{
    "title": "Phone call - making appointment",
    "title_zh": "打电话预约",
    "hsk_level": 2,
    "register": "neutral",
    "scenario_type": "dialogue",
    "difficulty": 0.5,
    "tree": {
        "setup": "You're calling a clinic to make a doctor's appointment.",
        "setup_zh": "你打电话给诊所预约看医生。",
        "turns": [
            {
                "speaker": "npc",
                "text_zh": "你好，这里是和平诊所。",
                "text_pinyin": "nǐ hǎo, zhèlǐ shì hépíng zhěnsuǒ.",
                "text_en": "Hello, this is Heping Clinic."
            },
            {
                "speaker": "player",
                "prompt_en": "Say you want to make an appointment.",
                "options": [
                    {
                        "text_zh": "你好，我想预约看医生。",
                        "text_pinyin": "nǐ hǎo, wǒ xiǎng yùyuē kàn yīshēng.",
                        "text_en": "Hello, I'd like to make an appointment to see a doctor.",
                        "score": 1.0,
                        "register": "neutral",
                        "feedback": "Clear and natural. 预约 is the standard word for appointments."
                    },
                    {
                        "text_zh": "我一般跑步和游泳，一周三四次吧。",
                        "text_pinyin": "wǒ yībān pǎobù hé yóuyǒng, yī zhōu sān sì cì ba.",
                        "text_en": "I usually run and swim, about three or four times a week.",
                        "score": 0.0,
                        "feedback": "Off-topic — you were asked to say you want to make an appointment, but this doesn't fit the conversation."
                    },
                    {
                        "text_zh": "好啊！星期六可以。",
                        "text_pinyin": "hǎo a! xīngqī liù kěyǐ.",
                        "text_en": "Sure! Saturday works.",
                        "score": 0.0,
                        "feedback": "Off-topic — you were asked to say you want to make an appointment, but this doesn't fit the conversation."
                    }
                ]
            },
            {
                "speaker": "npc",
                "text_zh": "好的。您想什么时候来？明天下午有空。",
                "text_pinyin": "hǎo de. nín xiǎng shénme shíhou lái? míngtiān xiàwǔ yǒu kòng.",
                "text_en": "OK. When would you like to come? Tomorrow afternoon is available."
            },
            {
                "speaker": "player",
                "prompt_en": "Accept the tomorrow afternoon slot.",
                "options": [
                    {
                        "text_zh": "我觉得先复习语法吧，那个部分我不太懂。",
                        "text_pinyin": "wǒ juéde xiān fùxí yǔfǎ ba, nà ge bùfen wǒ bú tài dǒng.",
                        "text_en": "I think we should start with grammar, I don't really understand that part.",
                        "score": 0.0,
                        "feedback": "Off-topic — you were asked to accept the tomorrow afternoon slot, but this doesn't fit the conversation."
                    },
                    {
                        "text_zh": "好的，明天下午可以。几点？",
                        "text_pinyin": "hǎo de, míngtiān xiàwǔ kěyǐ. jǐ diǎn?",
                        "text_en": "OK, tomorrow afternoon works. What time?",
                        "score": 1.0,
                        "register": "neutral",
                        "feedback": "Perfect — confirms and asks for specific time."
                    },
                    {
                        "text_zh": "下这么大的雨，太危险了，我们换个活动吧。",
                        "text_pinyin": "xià zhème dà de yǔ, tài wēixiǎn le, wǒmen huàn ge huódòng ba.",
                        "text_en": "With rain this heavy, it's too dangerous, let's switch to a different activity.",
                        "score": 0.0,
                        "feedback": "Off-topic — you were asked to accept the tomorrow afternoon slot, but this doesn't fit the conversation."
                    }
                ]
            }
        ],
        "cultural_note": "Phone calls in Chinese tend to be efficient. 预约 (yùyuē) is used for all formal appointments. On the phone, speaking clearly and confirming details is especially important."
    }
}